TdQrcode/TdQrcode.tox
TdQrcode/__init__.py
TdQrcode/extTdQrCode.py
tdp_qrcode-0.1.0.dist-info/licenses/LICENSE
tdp_qrcode-0.1.0.dist-info/METADATA
tdp_qrcode-0.1.0.dist-info/WHEEL
tdp_qrcode-0.1.0.dist-info/top_level.txt
tdp_qrcode-0.1.0.dist-info/RECORD
