Metadata-Version: 2.4
Name: tdp-QrCode
Version: 0.1.0
Summary: A prefab for TouchDesigner-Projects that will be complelty managed and run by UV.
Author-email: Wieland Hilker <wieland@plusplus.one>
Project-URL: Website, https://plusplus.one
Project-URL: Repository, https://github.com/PlusPlusOneGmbH/tdp-QrCode
Keywords: TouchDesigner,TOP,QrCode
Requires-Python: >=3.11
License-File: LICENSE
Requires-Dist: qrcode[pil]>=8.2
Dynamic: license-file
